mcp_mantis/__init__.py
mcp_mantis/server.py
mcp_mantis-0.0.1.dist-info/METADATA
mcp_mantis-0.0.1.dist-info/WHEEL
mcp_mantis-0.0.1.dist-info/entry_points.txt
mcp_mantis-0.0.1.dist-info/RECORD
